cuegui/AbstractDialog.py
cuegui/AbstractDockWidget.py
cuegui/AbstractGraphWidget.py
cuegui/AbstractTreeWidget.py
cuegui/AbstractWidgetItem.py
cuegui/Action.py
cuegui/App.py
cuegui/Comments.py
cuegui/ConfirmationDialog.py
cuegui/Constants.py
cuegui/CreateShowDialog.py
cuegui/CreatorDialog.py
cuegui/CueJobMonitorTree.py
cuegui/CueStateBarWidget.py
cuegui/Cuedepend.py
cuegui/DarkPalette.py
cuegui/DependDialog.py
cuegui/DependMonitorTree.py
cuegui/DependWizard.py
cuegui/EmailDialog.py
cuegui/Exception.py
cuegui/FilterDialog.py
cuegui/FrameMonitor.py
cuegui/FrameMonitorTree.py
cuegui/FrameRangeSelection.py
cuegui/GarbageCollector.py
cuegui/GroupDialog.py
cuegui/HostMonitor.py
cuegui/HostMonitorTree.py
cuegui/ItemDelegate.py
cuegui/JobMonitorGraph.py
cuegui/JobMonitorTree.py
cuegui/LayerDialog.py
cuegui/LayerMonitorTree.py
cuegui/Layout.py
cuegui/LimitSelectionWidget.py
cuegui/LimitsWidget.py
cuegui/LocalBooking.py
cuegui/Logger.py
cuegui/Main.py
cuegui/MainWindow.py
cuegui/MenuActions.py
cuegui/MiscDialog.py
cuegui/Plugins.py
cuegui/PreviewWidget.py
cuegui/ProcChildren.py
cuegui/ProcMonitor.py
cuegui/ProcMonitorTree.py
cuegui/ProgressDialog.py
cuegui/Redirect.py
cuegui/RequestCoresDialog.py
cuegui/ServiceDialog.py
cuegui/ShowDialog.py
cuegui/ShowsWidget.py
cuegui/SplashWindow.py
cuegui/Style.py
cuegui/SubscribeToJobDialog.py
cuegui/SubscriptionGraphWidget.py
cuegui/SubscriptionsWidget.py
cuegui/TagsWidget.py
cuegui/TasksDialog.py
cuegui/TextEditDialog.py
cuegui/ThreadPool.py
cuegui/UnbookDialog.py
cuegui/Utils.py
cuegui/__init__.py
cuegui/__main__.py
cuegui/eta.py
cuegui/config/cuecommander.ini
cuegui/config/cuegui.yaml
cuegui/config/cuetopia.ini
cuegui/config/darkpalette.qss
cuegui/config/gvimrc
cuegui/config/rqlog.vim
cuegui/cueguiplugin/.cueguipluginrc.yaml
cuegui/cueguiplugin/README.md
cuegui/cueguiplugin/__init__.py
cuegui/cueguiplugin/loader.py
cuegui/cueguiplugin/cueprogbar/__init__.py
cuegui/cueguiplugin/cueprogbar/__main__.py
opencue_cuegui-1.13.8.dist-info/METADATA
opencue_cuegui-1.13.8.dist-info/WHEEL
opencue_cuegui-1.13.8.dist-info/entry_points.txt
opencue_cuegui-1.13.8.dist-info/RECORD
