Metadata-Version: 2.1
Name: opencue_cuegui
Version: 1.13.8
Summary: CueGUI is the graphical user interface for OpenCue with two main workspace views. Cuetopia provides artist-focused tools for monitoring and managing render jobs through plugins like Monitor Jobs, Job Details, Frame logs, and Job Graph. CueCommander offers administrator-focused system monitoring and host management with advanced tools for allocations, hosts, services, and resources. Together, they enable artists and administrators to track job progress and manage render farm operations.
Requires-Python: >3.7
Requires-Dist: nodegraphqtpy==0.6.38.6
Requires-Dist: opencue-pycue
Requires-Dist: pyside2==5.15.2.1; python_version <= '3.10'
Requires-Dist: pyside6==6.5.3; python_version == '3.11'
Requires-Dist: pyside6==6.8.2.1; python_version > '3.11'
Requires-Dist: qtpy==2.4.1
Provides-Extra: test
Requires-Dist: mock==2.0.0; extra == 'test'
Requires-Dist: pyfakefs==5.2.3; extra == 'test'
Requires-Dist: pytest; extra == 'test'
